{
  "basics": {
    "name": "Daisaku Hayashi",
    "label": "Student",
    "picture": "https://dainnovation722.github.io/images/totoro.png",
    "email": "dhayashi@chemsys.t.u-tokyo.ac.jp",
    "phone": "808-333-4444",
    "website": "https://mmaluhia.github.io",
    "summary": "I am researching soft sensor in the Department of Chemical System Engineering at the University of Tokyo. I expect to graduate in Spring, 2021.",
    "location": {
      "address": "7-3-1 Hongo, Bunkyo Ward, Tokyo",
      "postalCode": "113－8656",
      "city": "Tokyo",
      "countryCode": "JAPAN",
      "region": "Kanto"
    },
    "profiles": [
      {
        "network": "github",
        "username": "dainnovation722",
        "url": "http://github.com/dainnovation722"
      },
      {
        "network": "twitter",
        "username": "dainnovation",
        "url": "https://twitter.com/cherrybachelor"
      }
    ]
  },
  "interests": [
    {
      "name": "Time-Series regression",
      "keywords": [
        "LSTM",
        "FFT"
      ]
    },
    {
      "name": "Transfer Learning",
      "keywords": [
        "domain adaptation",
        "adversarial transfer learning"        
      ]
    }
  ],
  "skills": [
    {
      "name": "Languages and Frameworks",
      "level": "",
      "keywords": [
        "Python",
        "C++",
        "Javascript",
        "html",
        "css"
      ]
    },
    {
      "name": "Toolsets/OS",
      "level": "",
      "keywords": [
        "MacOS",
        "Ubuntu",
        "Git/GitHub"
      ]
    }
  ],
  "education": [
    {
      "institution": "The University of Tokyo, Hongo, Tokyo",
      "area": "Chemical System Engineering",
      "studyType": "M.S.",
      "startDate": "2019-04-01",
      "endDate": "Present",
      "gpa": "",
      "courses": [
      ]
    }
  ],
  "intern": [
    {
      "company": "metadata",
      "position": "Algorithm Developer",
      "website": "https://metadata.co.jp/",
      "startDate": "2019-05-01",
      "endDate": "2019-10-31",
      "summary": "",
      "highlights": [
        "Implement, debug, refactoring algorithm for back-end web application"
      ]
    },
    {
      "company": "ALBERT",
      "position": "AI Developer",
      "website": "https://metadata.co.jp/",
      "startDate": "2019-09-02",
      "endDate": "2019-09-15",
      "summary" : "",
      "highlights": [
        "Develop AI for reversible game",
        "Writing report document"
      ]
    },
    {
      "company": "NABLAS",
      "position": "intern",
      "website": "https://nablas.com/",
      "startDate": "2019-09-15",
      "endDate": "Present",
      "summary": "",
      "highlights": [
        "Analysis for abnormal detection",
        "Consult for Chemical Manufacturer"
      ]
    }
  ]
}
